shapes/car.py
shapes/circle.py
shapes/rectangle.py
turtle_shapes-1.0.1.dist-info/METADATA
turtle_shapes-1.0.1.dist-info/WHEEL
turtle_shapes-1.0.1.dist-info/entry_points.txt
turtle_shapes-1.0.1.dist-info/top_level.txt
turtle_shapes-1.0.1.dist-info/RECORD
